{
	"has_precipitation": false,
	"temperature": 1,
	"downfall": 0,
	"effects": {
		"mood_sound": {
		"sound": "minecraft:ambient.cave",
		"tick_delay": 6000,
		"block_search_extent": 8,
		"offset": 2.0
	},
	"sky_color": 2905980,
	"foliage_color": 7372597,
	"grass_color": 8242525,
	"fog_color": 2509931,
	"water_color": 6836531,
	"water_fog_color": 5324584
	},
	"carvers": {
	},
	"features": [
		[],
		[
		],
		[],
		[
		],
		[],
		[],
		[
		],
		[],
		[
		],
		[
		]
	],
	"starts": [
	],
	"spawners": {
		"monster": [
		    ],
		"creature": [
				],
		"ambient": [
		    ],
		"water_creature": [
		],
		"water_ambient": [
		],
		"misc": []
	},
	"spawn_costs": {}
}